README
setup.py
ebv_helpers/__init__.py
ebv_helpers/core.py
ebv_helpers/envargumentparser.py
ebv_helpers/mapping.py
ebv_helpers/normalizer.py
ebv_helpers/queue_utils.py
ebv_helpers/timeutils.py
ebv_helpers/utils.py
ebv_helpers.egg-info/PKG-INFO
ebv_helpers.egg-info/SOURCES.txt
ebv_helpers.egg-info/dependency_links.txt
ebv_helpers.egg-info/requires.txt
ebv_helpers.egg-info/top_level.txt