Metadata-Version: 1.0
Name: ebv-helpers
Version: 1.0.32
Summary: helpers functions
Home-page: https://github.com/yasinmeydan/ebv_helpers.git
Author: UNKNOWN
Author-email: yasinmeydan@gmail.com
License: UNKNOWN
Platform: UNKNOWN
